Metadata-Version: 2.1
Name: CLinters
Version: 1.3.4
Summary: pre-commit hooks for C linters
Home-page: https://github.com/pocc/pre-commit-hooks
Author: Ross Jacobs
Author-email: rj@swit.sh
License: Apache2
Platform: UNKNOWN
Classifier: License :: OSI Approved :: Apache Software License
Classifier: Programming Language :: Python :: 3
Classifier: Programming Language :: Python :: 3 :: Only
Classifier: Programming Language :: Python :: 3.6
Classifier: Programming Language :: Python :: 3.7
Classifier: Programming Language :: Python :: 3.8
Requires-Python: >=3.6.1
